{
  "data": {
    "js": {
      "exclude": [
        "*.min.js",
        "**/*.min.js"
      ],
      "options": {
        "compress": {
          "dead_code": true
        },
        "mangle": {
          "toplevel": true,
          "safari10": true
        }
      }
    },
    "css": {
      "exclude": [
        "*.min.css",
        "**/*.min.css"
      ]
    },
    "html": {
      "fix": true,
      "exclude": [
        "*.min.{htm,html}"
      ],
      "collapseBooleanAttributes": true,
      "collapseWhitespace": true,
      "ignoreCustomComments": [
        {}
      ],
      "removeComments": true,
      "removeEmptyAttributes": true,
      "removeScriptTypeAttributes": true,
      "removeStyleLinkTypeAttributes": true,
      "minifyJS": true,
      "minifyCSS": true
    },
    "img": {
      "default": "https://upload.wikimedia.org/wikipedia/commons/6/65/No-Image-Placeholder.svg",
      "onerror": "serverside",
      "broken": false
    },
    "host": [
      "webmanajemen.com"
    ],
    "links": {
      "blank": true,
      "enable": true,
      "allow": [
        "webmanajemen.com"
      ],
      "exclude": [
        "webmanajemen.com",
        "web-manajemen.blogspot.com",
        "dimaslanjaka.github.io"
      ]
    },
    "schema": true,
    "sitemap": true
  }
}